odoo10_addon_hr_timesheet_holiday-10.0.1.0.1-nspkg.pth
odoo/addons/hr_timesheet_holiday/README.rst
odoo/addons/hr_timesheet_holiday/__init__.py
odoo/addons/hr_timesheet_holiday/__manifest__.py
odoo/addons/hr_timesheet_holiday/i18n/es.po
odoo/addons/hr_timesheet_holiday/i18n/fr.po
odoo/addons/hr_timesheet_holiday/i18n/hr_timesheet_holiday.pot
odoo/addons/hr_timesheet_holiday/i18n/it.po
odoo/addons/hr_timesheet_holiday/i18n/sl.po
odoo/addons/hr_timesheet_holiday/models/__init__.py
odoo/addons/hr_timesheet_holiday/models/analytic_account.py
odoo/addons/hr_timesheet_holiday/models/analytic_line.py
odoo/addons/hr_timesheet_holiday/models/company.py
odoo/addons/hr_timesheet_holiday/models/hr_holidays.py
odoo/addons/hr_timesheet_holiday/models/hr_holidays_status.py
odoo/addons/hr_timesheet_holiday/static/description/icon.png
odoo/addons/hr_timesheet_holiday/tests/__init__.py
odoo/addons/hr_timesheet_holiday/tests/test_all.py
odoo/addons/hr_timesheet_holiday/views/company_view.xml
odoo/addons/hr_timesheet_holiday/views/hr_holidays_view.xml
odoo10_addon_hr_timesheet_holiday-10.0.1.0.1.dist-info/METADATA
odoo10_addon_hr_timesheet_holiday-10.0.1.0.1.dist-info/WHEEL
odoo10_addon_hr_timesheet_holiday-10.0.1.0.1.dist-info/namespace_packages.txt
odoo10_addon_hr_timesheet_holiday-10.0.1.0.1.dist-info/top_level.txt
odoo10_addon_hr_timesheet_holiday-10.0.1.0.1.dist-info/RECORD
