Metadata-Version: 2.1
Name: odoo10-addon-hr-timesheet-holiday
Version: 10.0.1.0.1
Summary: When holidays are granted, add lines to the analytic account that is linked to the Leave Type
Home-page: https://github.com/OCA/hr-timesheet
Author: Sunflower IT, Therp BV, Odoo Community Association (OCA)
Author-email: support@odoo-community.org
License: AGPL-3
Platform: UNKNOWN
Classifier: Programming Language :: Python
Classifier: Framework :: Odoo
Classifier: License :: OSI Approved :: GNU Affero General Public License v3
Requires-Python: ~=2.7
Requires-Dist: odoo10-addon-hr-holidays-settings
Requires-Dist: odoo (<10.1dev,>=10.0)
